console_utilities.py
ruben_console_utilities-0.3.0.dist-info/LICENSE
ruben_console_utilities-0.3.0.dist-info/METADATA
ruben_console_utilities-0.3.0.dist-info/WHEEL
ruben_console_utilities-0.3.0.dist-info/top_level.txt
ruben_console_utilities-0.3.0.dist-info/RECORD
