Metadata-Version: 2.1
Name: ruben-console-utilities
Version: 0.3.0
Summary: Simple utility functions for command-line applications.
Home-page: https://github.com/Ruben9922/python-console-utilities
Author: Ruben Dougall
Author-email: info.ruebz999@gmail.com
Project-URL: Documentation, https://python-console-utilities.readthedocs.io/
Keywords: console command-line utilities
Classifier: Programming Language :: Python :: 3
Classifier: License :: OSI Approved :: GNU Lesser General Public License v3 (LGPLv3)
Classifier: Operating System :: OS Independent
Classifier: Environment :: Console
Classifier: Topic :: Software Development :: Libraries :: Python Modules
Requires-Python: >=3.6
License-File: LICENSE
